network_toolkit/__about__.py
network_toolkit/__init__.py
network_toolkit/__main__.py
network_toolkit/banner.py
network_toolkit/cli.py
network_toolkit/config.py
network_toolkit/credentials.py
network_toolkit/device.py
network_toolkit/device_transfers.py
network_toolkit/exceptions.py
network_toolkit/ip_device.py
network_toolkit/results_enhanced.py
network_toolkit/sequence_manager.py
network_toolkit/builtin_sequences/arista_eos/common.yml
network_toolkit/builtin_sequences/cisco_iosxe/common.yml
network_toolkit/builtin_sequences/cisco_nxos/common.yml
network_toolkit/builtin_sequences/juniper_junos/common.yml
network_toolkit/builtin_sequences/mikrotik_routeros/common.yml
network_toolkit/commands/__init__.py
network_toolkit/commands/backup.py
network_toolkit/commands/complete.py
network_toolkit/commands/config.py
network_toolkit/commands/diff.py
network_toolkit/commands/download.py
network_toolkit/commands/firmware.py
network_toolkit/commands/info.py
network_toolkit/commands/list.py
network_toolkit/commands/routerboard_upgrade.py
network_toolkit/commands/run.py
network_toolkit/commands/schema.py
network_toolkit/commands/sequence.py
network_toolkit/commands/ssh.py
network_toolkit/commands/ssh_engines.py
network_toolkit/commands/ssh_fallback.py
network_toolkit/commands/ssh_platform.py
network_toolkit/commands/upload.py
network_toolkit/commands/vendor_config_backup.py
network_toolkit/common/color_magic.py
network_toolkit/common/command.py
network_toolkit/common/command_base.py
network_toolkit/common/command_helpers.py
network_toolkit/common/config_manifest.py
network_toolkit/common/credentials.py
network_toolkit/common/defaults.py
network_toolkit/common/errors.py
network_toolkit/common/file_utils.py
network_toolkit/common/filename_utils.py
network_toolkit/common/interactive_confirmation.py
network_toolkit/common/logging.py
network_toolkit/common/output.py
network_toolkit/common/output_clean.py
network_toolkit/common/paths.py
network_toolkit/common/resolver.py
networka-0.1.13.dist-info/METADATA
networka-0.1.13.dist-info/WHEEL
networka-0.1.13.dist-info/entry_points.txt
networka-0.1.13.dist-info/licenses/LICENSE
networka-0.1.13.dist-info/RECORD
