Metadata-Version: 2.4
Name: networka
Version: 0.1.13
Summary: Modern Python cli toolkit for network device automation
Project-URL: Homepage, https://github.com/narrowin/networka
Project-URL: Documentation, https://narrowin.github.io/networka/
Project-URL: Repository, https://github.com/narrowin/networka.git
Project-URL: Bug Tracker, https://github.com/narrowin/networka/issues
Project-URL: Changelog, https://github.com/narrowin/networka/blob/main/CHANGELOG.md
Project-URL: Source Code, https://github.com/narrowin/networka
Project-URL: CI/CD, https://github.com/narrowin/networka/actions
Author-email: narrowin <contact@narrowin.com>
Maintainer-email: narrowin <contact@narrowin.com>
License: Apache-2.0
License-File: LICENSE
Keywords: async,automation,cli,infrastructure,mikrotik,narrowin,network,networking,routeros
Classifier: Development Status :: 4 - Beta
Classifier: Environment :: Console
Classifier: Intended Audience :: Developers
Classifier: Intended Audience :: System Administrators
Classifier: Intended Audience :: Telecommunications Industry
Classifier: License :: OSI Approved :: Apache Software License
Classifier: Operating System :: MacOS
Classifier: Operating System :: Microsoft :: Windows
Classifier: Operating System :: OS Independent
Classifier: Operating System :: POSIX :: Linux
Classifier: Programming Language :: Python :: 3
Classifier: Programming Language :: Python :: 3 :: Only
Classifier: Programming Language :: Python :: 3.11
Classifier: Programming Language :: Python :: 3.12
Classifier: Programming Language :: Python :: 3.13
Classifier: Topic :: Software Development :: Libraries :: Python Modules
Classifier: Topic :: System :: Networking
Classifier: Topic :: System :: Systems Administration
Classifier: Topic :: Utilities
Classifier: Typing :: Typed
Requires-Python: >=3.11
Requires-Dist: asyncssh>=2.21.0
Requires-Dist: libtmux>=0.46.2
Requires-Dist: pydantic>=2.5.0
Requires-Dist: python-dotenv>=1.0.0
Requires-Dist: pyyaml>=6.0
Requires-Dist: rich>=13.0.0
Requires-Dist: scrapli-community>=2025.1.30
Requires-Dist: scrapli[community]>=2023.7.30
Requires-Dist: scrapli[paramiko]>=2023.7.30
Requires-Dist: textual>=0.58.0
Requires-Dist: typer>=0.12.0
Provides-Extra: dev
Requires-Dist: bandit>=1.7.0; extra == 'dev'
Requires-Dist: build>=0.10.0; extra == 'dev'
Requires-Dist: cffconvert>=2.0.0; extra == 'dev'
Requires-Dist: detect-secrets>=1.4.0; extra == 'dev'
Requires-Dist: mypy>=1.7.0; extra == 'dev'
Requires-Dist: pytest-asyncio>=0.21.0; extra == 'dev'
Requires-Dist: pytest-cov>=4.1.0; extra == 'dev'
Requires-Dist: pytest-mock>=3.14.0; extra == 'dev'
Requires-Dist: pytest-xdist>=3.8.0; extra == 'dev'
Requires-Dist: pytest>=7.4.0; extra == 'dev'
Requires-Dist: ruff>=0.1.0; extra == 'dev'
Requires-Dist: twine>=4.0.0; extra == 'dev'
Requires-Dist: types-paramiko>=3.0.0; extra == 'dev'
Requires-Dist: types-pyyaml>=6.0.0; extra == 'dev'
Provides-Extra: docs
Requires-Dist: mkdocs-material>=9.0.0; extra == 'docs'
Requires-Dist: mkdocs>=1.5.0; extra == 'docs'
Requires-Dist: mkdocstrings[python]>=0.24.0; extra == 'docs'
Provides-Extra: tmux
Requires-Dist: libtmux>=0.21.0; extra == 'tmux'
